{
  "name": "Fiendborn",
  "type": "ancestry",
  "img": "icons/creatures/unholy/demon-horned-winged-laughing.webp",
  "system": {
    "description": "<p><span style=\"text-decoration: underline;\"><strong>Fiendish Origin</strong></span></p>\n<p>Choose a Fiendish Origin from the following list: Fire, Cold, Acid, Poison, and Unholy. All future choices within this Ancestry must use the chosen Fiendish Origin. The&nbsp;type of damage associated with your Fiendish Origin is your&nbsp;Fiendish damage.</p>\n<p><span style=\"text-decoration: underline;\"><strong>Fiendborn Redemption</strong></span></p>\n<p>If you choose to play a Fiendborn and go down a path of bredemption, you can choose to be a Redeemed Fiendborn.&nbsp;This can happen at character creation from good acts done&nbsp;from your backstory, or this can happen mid campaign after a&nbsp;large change in your character.&nbsp;You gain the following Ancestry Trait:</p>\n<p>@UUID[Compendium.dc20rpg.ancestries.Item.htQDINprc4d7PIiX]{Redeemed}</p>\n<p>&nbsp;</p>\n<h2>Default Traits</h2>\n<p>&nbsp;</p>\n<p>&nbsp;</p>\n<h2>Expanded Traits</h2>",
    "tableName": "",
    "source": "",
    "movement": {
      "speed": 4,
      "burrow": false,
      "climbing": false,
      "flying": false,
      "swimming": false
    },
    "vision": {
      "darkvision": 0,
      "tremorsense": 0,
      "blindsight": 0,
      "truesight": 0
    },
    "size": "medium",
    "scaling": {},
    "advancements": {}
  },
  "effects": [],
  "folder": "OaKw7YTlF6jxlj6g",
  "flags": {
    "core": {}
  },
  "_stats": {
    "systemId": "dc20rpg",
    "systemVersion": "0.4.0",
    "coreVersion": "11.315",
    "createdTime": 1703715811208,
    "modifiedTime": 1703720919143,
    "lastModifiedBy": "4DVAPNxi8Z6Oo6UP"
  },
  "_id": "NgpuViQG9RmVDJHX",
  "sort": 0,
  "ownership": {
    "default": 0,
    "4DVAPNxi8Z6Oo6UP": 3
  },
  "_key": "!items!NgpuViQG9RmVDJHX"
}
