{
  "name": "Holy Weakness",
  "type": "feature",
  "img": "icons/magic/light/beam-red-orange.webp",
  "system": {
    "description": "<p>You have Holy Vulnerable 1.</p>",
    "tableName": "Ancestry",
    "source": "",
    "isReaction": false,
    "actionType": "",
    "attackFormula": {
      "checkType": "attack",
      "rollBonus": 0,
      "combatMastery": true,
      "critThreshold": 20,
      "overriden": false,
      "formula": "",
      "overridenFormula": ""
    },
    "duration": {
      "value": null,
      "type": "instantaneous",
      "timeUnit": ""
    },
    "range": {
      "normal": null,
      "max": null,
      "unit": ""
    },
    "target": {
      "area": "",
      "count": null,
      "distance": null,
      "invidual": true,
      "type": "",
      "unit": "",
      "width": null
    },
    "check": {
      "canCrit": false,
      "checkKey": "",
      "contestedKey": "",
      "checkDC": null,
      "eachFiveForumla": "",
      "failFormula": ""
    },
    "formulas": {},
    "save": {
      "type": "",
      "dc": null,
      "calculationKey": "spell",
      "addMastery": false
    },
    "costs": {
      "resources": {
        "actionPoint": null,
        "stamina": null,
        "mana": null,
        "health": null,
        "custom": {}
      },
      "charges": {
        "current": null,
        "max": null,
        "maxChargesFormula": "",
        "overriden": false,
        "rechargeFormula": "",
        "reset": "",
        "showAsResource": false
      },
      "otherItem": {
        "itemId": "",
        "amountConsumed": 0,
        "consumeCharge": true
      }
    },
    "featureType": "ancestry",
    "featureOrigin": "Fiendborn 1",
    "usesWeapon": "",
    "activableEffect": {
      "hasEffects": false,
      "active": false
    },
    "rollMenu": {
      "showMenu": false,
      "dis": 0,
      "adv": 0,
      "free": false,
      "versatile": false
    },
    "enhancements": {}
  },
  "effects": [
    {
      "icon": "icons/magic/light/beam-red-orange.webp",
      "origin": "Item.6tWd8HRWT1yJCokU",
      "duration": {
        "startTime": null,
        "seconds": null,
        "combat": null,
        "rounds": null,
        "turns": null,
        "startRound": null,
        "startTurn": null
      },
      "disabled": false,
      "name": "Holy Weakness",
      "_id": "JygVShmaXMXeFEpZ",
      "changes": [
        {
          "key": "system.damageReduction.damageTypes.holy.vulnerable",
          "mode": 2,
          "value": "1",
          "priority": null
        }
      ],
      "description": "",
      "transfer": true,
      "statuses": [],
      "flags": {},
      "tint": null,
      "_key": "!items.effects!PfSFgJpVAPme02dy.JygVShmaXMXeFEpZ"
    }
  ],
  "folder": "DjSBTbBU86YAZLmP",
  "flags": {
    "core": {}
  },
  "_stats": {
    "systemId": "dc20rpg",
    "systemVersion": "0.4.0",
    "coreVersion": "11.315",
    "createdTime": 1703712052182,
    "modifiedTime": 1703720932569,
    "lastModifiedBy": "4DVAPNxi8Z6Oo6UP"
  },
  "_id": "PfSFgJpVAPme02dy",
  "sort": 0,
  "ownership": {
    "default": 0,
    "4DVAPNxi8Z6Oo6UP": 3
  },
  "_key": "!items!PfSFgJpVAPme02dy"
}
