{
  "name": "Crossbow Maneuver",
  "type": "technique",
  "img": "icons/weapons/crossbows/crossbow-white.webp",
  "system": {
    "description": "<p><strong>Style Passive:</strong> Your <strong>Attack Checks </strong>score a <strong>Critical Hit </strong>on a d20 roll of <strong>19 </strong>or <strong>20 </strong>against targets that are within 5 Spaces.</p>\n<p>Additionally, you do not have DisADV on Attack Checks made using a Crossbow Weapon as a result of being underwater.</p>\n<p><strong>Requires: </strong>Attack Check</p>\n<p><strong>Maneuver: (1 AP)</strong> As part of an <strong>Attack Check</strong>, you can move up to 2 Spaces towards your target without provoking Opportunity Attacks.</p>\n<p>&nbsp;</p>\n<p><em><strong>System Tip: </strong>You can add Weapon Maneuvers as Weapon Enhacements for easier use. Just press \"Add Martial Maneuvers For Weapon\" on <strong>Enhancements </strong>tab on <strong>Item </strong>sheet.</em></p>",
    "tableName": "Weapon Maneuvers",
    "source": "",
    "isReaction": false,
    "actionType": "",
    "attackFormula": {
      "checkType": "attack",
      "rollBonus": 0,
      "combatMastery": true,
      "critThreshold": 20,
      "overriden": false,
      "formula": "",
      "overridenFormula": ""
    },
    "duration": {
      "value": null,
      "type": "instantaneous",
      "timeUnit": ""
    },
    "range": {
      "normal": null,
      "max": null,
      "unit": ""
    },
    "target": {
      "area": "",
      "count": null,
      "distance": null,
      "invidual": true,
      "type": "",
      "unit": "",
      "width": null
    },
    "check": {
      "canCrit": false,
      "checkKey": "att",
      "contestedKey": "phy",
      "checkDC": null,
      "eachFiveForumla": "",
      "failFormula": ""
    },
    "formulas": {},
    "save": {
      "type": "phy",
      "dc": null,
      "calculationKey": "martial",
      "addMastery": false
    },
    "costs": {
      "resources": {
        "actionPoint": 1,
        "stamina": null,
        "mana": null,
        "health": null,
        "custom": {}
      },
      "charges": {
        "current": null,
        "max": null,
        "maxChargesFormula": "",
        "overriden": false,
        "rechargeFormula": "",
        "reset": "",
        "showAsResource": false
      },
      "otherItem": {
        "itemId": "",
        "amountConsumed": 0,
        "consumeCharge": true
      }
    },
    "techniqueType": "maneuver",
    "techniqueOrigin": "Weapon",
    "usesWeapon": "",
    "activableEffect": {
      "hasEffects": false,
      "active": false
    },
    "rollMenu": {
      "showMenu": false,
      "dis": 0,
      "adv": 0,
      "free": false,
      "versatile": false
    },
    "enhancements": {}
  },
  "effects": [],
  "folder": "Ow9TCbd4obhoo9Eq",
  "sort": 100000,
  "ownership": {
    "default": 0,
    "esZhExLF9SPQJF4M": 3
  },
  "flags": {
    "core": {
      "sourceId": "Item.2gzia6ZADY6S3Vw1"
    }
  },
  "_stats": {
    "systemId": "dc20rpg",
    "systemVersion": "0.4.0",
    "coreVersion": "11.308",
    "createdTime": 1703527164335,
    "modifiedTime": 1703533835338,
    "lastModifiedBy": "esZhExLF9SPQJF4M"
  },
  "_id": "SF5B0O5ZhLalm8rz",
  "_key": "!items!SF5B0O5ZhLalm8rz"
}
