{
  "name": "Entangle",
  "type": "spell",
  "img": "icons/magic/nature/root-vine-entangled-humanoid.webp",
  "system": {
    "itemKey": "",
    "description": "<p><span class=\"cf0\">You conjure a 3 Space diameter Sphere of natural phenomenon (such as entangling plants) within range. The area becomes Difficult Terrain for the duration.</span></p><p><span class=\"cf0\">Make a Spell Check against the Agility Save of each creature in the area.</span></p><p><span class=\"cf0\"><strong>Save Failure:</strong> The target becomes Immobilized for the duration or until its Space is cleared of the effect. The target can also spend 1 AP to repeat its Save, ending the Condition on itself on a Success.</span></p><p><span class=\"cf0\"><strong>Clearing Spaces: </strong>Each Space within the area has an AD and PD equal to your Save DC and is cleared when it takes an amount of Elemental or Slashing damage equal to the MP spent on the Spell (minimum of 1).</span></p><p><em><strong>System Tip:</strong> Clearing Spaces is not automated.</em></p><p><span class=\"cf0\"><em><strong>Example:</strong> A 1st level Druid casts Entangle using 1 MP, each Space has a PD and AD or 14 (equal to Save DC) and needs to take 1 Fire or Slashing damage to be cleared (equal to 1 MP spent to cast the Spell)</em></span></p><p></p><p><span style=\"text-decoration: underline;\"><strong><span style=\"text-decoration: underline;\">Spell Enhancements</span></strong></span></p><p><strong>Range: (1 AP, Repeatable) </strong>The range of the Spell increases by 5 Spaces. You can use this Enhancement a maximum of two times.</p><p><strong>Area: (</strong><span style=\"color:rgba(44, 44, 43, 1);isolation:auto\" data-token-index=\"0\" class=\"notion-enable-hover\"><strong>X MP</strong></span><strong>)</strong> The diameter of the Sphere increases by X Space.</p><p><strong>Grasping:</strong> <strong>(2 MP)</strong> When a creature enters the area for the first time on its turn or starts its turn there, it makes an Agility Save against your Save DC. <strong>Save Failure:</strong> The target is Immobilized.</p><p><strong>Restrained: (2 MP)</strong> Creatures Immobilized by Entangle are Restrained.</p><p><strong>Spikey Terrain: (X MP)</strong> Creatures take X Piercing damage when they enter an Entangled Space after the Spell has been cast. They also take this damage if they fail a Save to end the Immobilized Condition inflicted by this Spell.</p>",
    "shortInfo": "",
    "tableName": "",
    "source": "",
    "choicePointCost": 1,
    "requirements": {
      "level": 0,
      "items": ""
    },
    "rollMenu": {
      "free": false,
      "rangeType": "",
      "versatile": false,
      "flanks": false,
      "halfCover": false,
      "tqCover": false,
      "dis": 0,
      "adv": 0,
      "apCost": 0,
      "gritCost": 0,
      "autoCrit": false,
      "autoFail": false,
      "coreFormula": {
        "modifier": "",
        "source": ""
      },
      "help": [],
      "ignoreMCP": false
    },
    "hideFromCompendiumBrowser": false,
    "quickRoll": false,
    "macros": {},
    "usable": true,
    "isReaction": false,
    "help": {
      "ignoreMHP": false,
      "subtract": false,
      "duration": "round"
    },
    "toggle": {
      "toggleable": false,
      "toggledOn": false,
      "toggleOnRoll": false
    },
    "actionType": "check",
    "attackFormula": {
      "rangeType": "",
      "checkType": "spell",
      "targetDefence": "precision",
      "rollBonus": 0,
      "combatMastery": true,
      "critThreshold": 20,
      "halfDmgOnMiss": false,
      "skipBonusDamage": {
        "heavy": false,
        "brutal": false,
        "crit": false,
        "conditionals": false
      },
      "ignoreCloseQuarters": false,
      "formulaMod": ""
    },
    "check": {
      "canCrit": false,
      "checkKey": "spe",
      "multiCheck": {
        "active": false,
        "options": {}
      },
      "contestedKey": "phy",
      "againstDC": false,
      "checkDC": 10,
      "respectSizeRules": false,
      "failEffect": ""
    },
    "save": {
      "type": "phy",
      "dc": 0,
      "calculationKey": "spell",
      "addMastery": false,
      "failEffect": ""
    },
    "costs": {
      "resources": {
        "actionPoint": null,
        "ap": 2,
        "stamina": null,
        "mana": 1,
        "health": null,
        "grit": null,
        "restPoints": null,
        "custom": {}
      },
      "charges": {
        "current": null,
        "max": null,
        "maxChargesFormula": "",
        "overriden": false,
        "rechargeFormula": "",
        "rechargeDice": "",
        "requiredTotalMinimum": null,
        "reset": "",
        "showAsResource": false,
        "subtract": 1,
        "deleteOnZero": false
      }
    },
    "againstEffect": {
      "id": "",
      "supressFromChatMessage": false,
      "untilYourNextTurnStart": false,
      "untilYourNextTurnEnd": false,
      "untilTargetNextTurnStart": false,
      "untilTargetNextTurnEnd": false,
      "untilFirstTimeTriggered": false
    },
    "againstStatuses": {
      "ZheoPdWs2Fzt1Now": {
        "id": "immobilized",
        "supressFromChatMessage": true,
        "untilYourNextTurnStart": false,
        "untilYourNextTurnEnd": false,
        "untilTargetNextTurnStart": false,
        "untilTargetNextTurnEnd": false,
        "untilFirstTimeTriggered": false,
        "forOneMinute": false,
        "repeatedSave": false,
        "repeatedSaveKey": "phy",
        "forXRounds": null,
        "stacks": null
      }
    },
    "rollRequests": {
      "deilROwiLvgZZUIw": {
        "category": "contest",
        "saveKey": "agi",
        "contestedKey": "agi",
        "dcCalculation": "spell",
        "dc": 0,
        "addMasteryToDC": true
      }
    },
    "formulas": {},
    "enhancements": {
      "eqPXCSdsRVTOQ6o3": {
        "name": "Range",
        "number": 0,
        "preventModification": false,
        "description": "<p>The range of the Spell increases by 5 Spaces. You can use this Enhancement a maximum of two times.</p>",
        "hide": false,
        "resources": {
          "ap": 1,
          "health": null,
          "mana": null,
          "stamina": null,
          "grit": null,
          "restPoints": null,
          "custom": {}
        },
        "charges": {
          "subtract": null,
          "fromOriginal": false
        },
        "modifications": {
          "modifiesCoreFormula": false,
          "coreFormulaModification": "",
          "overrideTargetDefence": false,
          "targetDefenceType": "area",
          "hasAdditionalFormula": false,
          "additionalFormula": "",
          "specificFormulaKey": "",
          "overrideDamageType": false,
          "damageType": "",
          "addsNewFormula": false,
          "formula": {
            "formula": "",
            "type": "",
            "category": "damage",
            "fail": false,
            "failFormula": "",
            "dontModifyFailFormula": false,
            "each5": false,
            "each5Formula": "",
            "dontMerge": false,
            "overrideDefence": "",
            "perTarget": false
          },
          "addsNewRollRequest": false,
          "rollRequest": {
            "category": "save",
            "saveKey": "",
            "contestedKey": "",
            "dcCalculation": "spell",
            "dc": 0,
            "addMasteryToDC": true
          },
          "addsAgainstStatus": false,
          "againstStatus": {
            "id": "",
            "supressFromChatMessage": false,
            "untilYourNextTurnStart": false,
            "untilYourNextTurnEnd": false,
            "untilTargetNextTurnStart": false,
            "untilTargetNextTurnEnd": false,
            "untilFirstTimeTriggered": false,
            "forOneMinute": false,
            "repeatedSave": false,
            "repeatedSaveKey": "phy"
          },
          "addsEffect": null,
          "macros": {
            "preItemRoll": "",
            "postItemRoll": ""
          },
          "rollLevelChange": false,
          "rollLevel": {
            "type": "adv",
            "value": 1
          },
          "addsRange": true,
          "bonusRange": {
            "melee": null,
            "normal": 5,
            "max": null
          },
          "changeManaSpendLimit": 0,
          "changeStaminaSpendLimit": 0,
          "changeDuration": false,
          "duration": {
            "value": null,
            "type": "",
            "timeUnit": ""
          },
          "actionChange": false,
          "actionType": ""
        },
        "key": "eqPXCSdsRVTOQ6o3",
        "sourceItemId": "cvsHJBsmJ6lTQpg4",
        "sourceItemName": "Entangle",
        "sourceItemImg": "icons/magic/nature/root-vine-entangled-humanoid.webp",
        "active": false,
        "drmCheck": true,
        "repeatable": true,
        "defaultState": 0,
        "copyToSheetRoll": {},
        "altCostMax": 0,
        "altCost": 0
      },
      "R0wDEHqm4E7aKr89": {
        "name": "Area",
        "number": 0,
        "preventModification": false,
        "description": "<p>The diameter of the Sphere increases by 1 Space.</p>",
        "hide": false,
        "resources": {
          "ap": "",
          "health": "",
          "mana": "1",
          "stamina": "",
          "grit": "",
          "restPoints": "",
          "custom": {}
        },
        "charges": {
          "subtract": null,
          "fromOriginal": false
        },
        "modifications": {
          "modifiesCoreFormula": false,
          "coreFormulaModification": "",
          "overrideTargetDefence": false,
          "targetDefenceType": "area",
          "hasAdditionalFormula": false,
          "additionalFormula": "",
          "specificFormulaKey": "",
          "overrideDamageType": false,
          "damageType": "",
          "addsNewFormula": false,
          "formula": {
            "formula": "",
            "type": "",
            "category": "damage",
            "fail": false,
            "failFormula": "",
            "dontModifyFailFormula": false,
            "each5": false,
            "each5Formula": "",
            "dontMerge": false,
            "overrideDefence": "",
            "perTarget": false
          },
          "addsNewRollRequest": false,
          "rollRequest": {
            "category": "save",
            "saveKey": "",
            "contestedKey": "",
            "dcCalculation": "spell",
            "dc": 0,
            "addMasteryToDC": true
          },
          "addsAgainstStatus": false,
          "againstStatus": {
            "id": "",
            "supressFromChatMessage": false,
            "untilYourNextTurnStart": false,
            "untilYourNextTurnEnd": false,
            "untilTargetNextTurnStart": false,
            "untilTargetNextTurnEnd": false,
            "untilFirstTimeTriggered": false,
            "forOneMinute": false,
            "repeatedSave": false,
            "repeatedSaveKey": "phy"
          },
          "addsEffect": null,
          "macros": {
            "preItemRoll": "",
            "postItemRoll": ""
          },
          "rollLevelChange": false,
          "rollLevel": {
            "type": "adv",
            "value": 1
          },
          "addsRange": false,
          "bonusRange": {
            "melee": null,
            "normal": null,
            "max": null
          },
          "changeManaSpendLimit": 0,
          "changeStaminaSpendLimit": 0,
          "changeDuration": false,
          "duration": {
            "value": null,
            "type": "",
            "timeUnit": ""
          },
          "actionChange": false,
          "actionType": "",
          "areaDistance": "1",
          "areaWidth": "",
          "overrideAreaType": ""
        },
        "key": "R0wDEHqm4E7aKr89",
        "sourceItemId": "cvsHJBsmJ6lTQpg4",
        "sourceItemName": "Entangle",
        "sourceItemImg": "icons/magic/nature/root-vine-entangled-humanoid.webp",
        "active": false,
        "repeatable": true,
        "defaultState": 0,
        "copyToSheetRoll": {},
        "altCostMax": 0,
        "altCost": 0,
        "drmCheck": false
      },
      "gARfpLHZb5kvjFNb": {
        "name": "Grasping",
        "number": 0,
        "preventModification": false,
        "description": "<p><strong>(Sustained)</strong> When a creature enters the area for the first time on its turn or starts its turn there, it makes an Agility Save against your Save DC.</p><p><strong>Save Failure:</strong> The target is Immobilized.</p>",
        "hide": false,
        "resources": {
          "ap": "",
          "health": "",
          "mana": "1",
          "stamina": "",
          "grit": "",
          "restPoints": "",
          "custom": {}
        },
        "charges": {
          "subtract": null,
          "fromOriginal": false
        },
        "modifications": {
          "modifiesCoreFormula": false,
          "coreFormulaModification": "",
          "overrideTargetDefence": false,
          "targetDefenceType": "area",
          "hasAdditionalFormula": false,
          "additionalFormula": "",
          "specificFormulaKey": "",
          "overrideDamageType": false,
          "damageType": "",
          "addsNewFormula": false,
          "formula": {
            "formula": "",
            "type": "",
            "category": "damage",
            "fail": false,
            "failFormula": "",
            "dontModifyFailFormula": false,
            "each5": false,
            "each5Formula": "",
            "dontMerge": false,
            "overrideDefence": "",
            "perTarget": false
          },
          "addsNewRollRequest": false,
          "rollRequest": {
            "category": "save",
            "saveKey": "",
            "contestedKey": "",
            "dcCalculation": "spell",
            "dc": 0,
            "addMasteryToDC": true
          },
          "addsAgainstStatus": false,
          "againstStatus": {
            "id": "",
            "supressFromChatMessage": false,
            "untilYourNextTurnStart": false,
            "untilYourNextTurnEnd": false,
            "untilTargetNextTurnStart": false,
            "untilTargetNextTurnEnd": false,
            "untilFirstTimeTriggered": false,
            "forOneMinute": false,
            "repeatedSave": false,
            "repeatedSaveKey": "phy"
          },
          "addsEffect": {
            "name": "Grasping",
            "img": "icons/magic/nature/root-vine-entangle-foot-green.webp",
            "origin": null,
            "duration": {
              "rounds": 1,
              "startTime": 0,
              "combat": null,
              "seconds": null,
              "startRound": 50,
              "startTurn": 0,
              "value": 1,
              "units": "rounds",
              "expiry": "turnStart",
              "expired": false
            },
            "disabled": false,
            "flags": {
              "dc20rpg": {
                "enhKey": "gARfpLHZb5kvjFNb",
                "itemSavePath": "system.enhancements.gARfpLHZb5kvjFNb.modifications.addsEffect"
              }
            },
            "_id": "pY6t3lvEpuRjGhig",
            "type": "base",
            "system": {
              "sustained": {
                "isSustained": false,
                "actorUuid": "",
                "itemId": ""
              },
              "statusId": "",
              "condition": false,
              "fromStatus": false,
              "duration": {
                "useCounter": false,
                "resetWhenEnabled": false,
                "onTimeEnd": "",
                "expiryAction": ""
              },
              "effectKey": "",
              "macro": "if (actor.hasStatus(\"immobilized\")) return;\nconst effectData = effect.flags.dc20rpg?.entangle;\nif (!effectData) return;\n\neffectData.system.changes[0].value = effectData.system.changes[0].value.replace('\"against\": <#@saveDC.value.spell#>', `\"against\": ${event.against}`);\n\n// We dont want to call it too fast as some tokens might be inside that template at the time we place it.\nconst skipTime = 5000 // 5 sec\nconst templateCallTime = effect.flags.dc20rpg?.templateCallTime || 0;\nconst effectCreationTime = effect._stats.createdTime\nif (event.trigger === \"instant\" && effectCreationTime - templateCallTime < skipTime) return;\n\nconst details = DC20.DC20Roll.prepareSaveDetails(\"agi\", {against: event.against, statuses: effectData.statuses, rollTitle: event.label});\nconst roll = await DC20.dialog.RollDialog.open(actor, details, {sendToActorOwners: true});\nif (roll && (roll._total < event.against)) {\n  game.dc20rpg.effects.createEffectOn(effectData, actor);\n}",
              "addToChat": true,
              "applyToTemplate": true,
              "nonessential": false,
              "disableWhen": {
                "path": "",
                "mode": "",
                "value": ""
              },
              "enableStatusOnCreation": [],
              "disableStatusOnRemoval": [],
              "requireEnhancement": "",
              "chatMessageId": "",
              "changes": [
                {
                  "key": "system.events",
                  "value": "\"eventType\": \"macro\", \"trigger\": \"turnStart\", \"label\": \"Grasping\", \"actorId\": \"#SPEAKER_ID#\", \"against\": <#@saveDC.value.spell#>",
                  "priority": null,
                  "useCustom": false,
                  "type": "add",
                  "phase": "initial"
                },
                {
                  "key": "system.events",
                  "value": "\"eventType\": \"macro\", \"trigger\": \"instant\", \"label\": \"Grasping\", \"actorId\": \"#SPEAKER_ID#\", \"against\": <#@saveDC.value.spell#>",
                  "priority": null,
                  "useCustom": false,
                  "type": "add",
                  "phase": "initial"
                }
              ],
              "applyToSelf": false,
              "requireEquip": false,
              "refreshTarget": false
            },
            "description": "<p>When a creature enters the area for the first time on its turn or starts its turn there, it makes an Agility Save against your Save DC.</p><p><strong>Save Failure:</strong> The target is Immobilized.</p>",
            "tint": "#ffffff",
            "transfer": true,
            "statuses": [],
            "sort": 0,
            "_stats": {
              "compendiumSource": null,
              "duplicateSource": null,
              "exportSource": null,
              "coreVersion": "14.363",
              "systemId": "dc20rpg",
              "systemVersion": "0.10.6.0",
              "createdTime": 1782631316570,
              "modifiedTime": 1782631341971,
              "lastModifiedBy": "dOcXwrUs2VunZl0y"
            },
            "start": {
              "combat": null,
              "round": 50,
              "time": 0,
              "turn": 0,
              "combatant": null,
              "initiative": null
            },
            "showIcon": 1,
            "folder": null
          },
          "macros": {
            "preItemRoll": "",
            "postItemRoll": "const entangle = item.getEffectByKey(\"entangle\");\nif (!entangle) return;\n\nenh.modifications.addsEffect.flags.dc20rpg.entangle = entangle.toObject(false);"
          },
          "rollLevelChange": false,
          "rollLevel": {
            "type": "adv",
            "value": 1
          },
          "addsRange": false,
          "bonusRange": {
            "melee": null,
            "normal": null,
            "max": null
          },
          "changeManaSpendLimit": 0,
          "changeStaminaSpendLimit": 0,
          "changeDuration": false,
          "duration": {
            "value": null,
            "type": "",
            "timeUnit": ""
          },
          "actionChange": false,
          "actionType": "",
          "areaDistance": "",
          "areaWidth": "",
          "overrideAreaType": ""
        },
        "key": "gARfpLHZb5kvjFNb",
        "sourceItemId": "cvsHJBsmJ6lTQpg4",
        "sourceItemName": "Entangle",
        "sourceItemImg": "icons/magic/nature/root-vine-entangled-humanoid.webp",
        "active": false,
        "repeatable": true,
        "defaultState": 0,
        "copyToSheetRoll": {},
        "altCostMax": 0,
        "altCost": 0,
        "drmCheck": false
      },
      "aTade7nOb9Uj6HSe": {
        "name": "Restrained",
        "number": 0,
        "preventModification": false,
        "description": "<p>Creatures Immobilized by Entangle are Restrained.</p>",
        "hide": false,
        "resources": {
          "ap": "",
          "health": "",
          "mana": "2",
          "stamina": "",
          "grit": "",
          "restPoints": "",
          "custom": {}
        },
        "charges": {
          "subtract": null,
          "fromOriginal": false
        },
        "modifications": {
          "modifiesCoreFormula": false,
          "coreFormulaModification": "",
          "overrideTargetDefence": false,
          "targetDefenceType": "area",
          "hasAdditionalFormula": false,
          "additionalFormula": "",
          "specificFormulaKey": "",
          "overrideDamageType": false,
          "damageType": "",
          "addsNewFormula": false,
          "formula": {
            "formula": "",
            "type": "",
            "category": "damage",
            "fail": false,
            "failFormula": "",
            "dontModifyFailFormula": false,
            "each5": false,
            "each5Formula": "",
            "dontMerge": false,
            "overrideDefence": "",
            "perTarget": false
          },
          "addsNewRollRequest": false,
          "rollRequest": {
            "category": "save",
            "saveKey": "",
            "contestedKey": "",
            "dcCalculation": "spell",
            "dc": 0,
            "addMasteryToDC": true
          },
          "addsAgainstStatus": true,
          "againstStatus": {
            "id": "restrained",
            "supressFromChatMessage": true,
            "untilYourNextTurnStart": false,
            "untilYourNextTurnEnd": false,
            "untilTargetNextTurnStart": false,
            "untilTargetNextTurnEnd": false,
            "untilFirstTimeTriggered": false,
            "forOneMinute": false,
            "repeatedSave": false,
            "repeatedSaveKey": "phy",
            "forXRounds": null,
            "stacks": null
          },
          "addsEffect": null,
          "macros": {
            "preItemRoll": "const effect = item.getEffectByKey(\"entangle\");\nif (!effect) return;\n\n\n\neffect.statuses.add(\"restrained\");\neffect.statuses.add(\"grappled\");\neffect.system.changes.forEach(change => {\n  if (change.key === \"system.events\" && change.value.includes('\"statuses\": [\"immobilized\"]')) {\n    change.value = change.value.replace('\"statuses\": [\"immobilized\"]', '\"statuses\": [\"immobilized\", \"restrained\"]');\n  }\n})\n\n\neffect.system.changes.push({\n  key: \"system.dynamicRollModifier.onYou.attack\",\n  mode: 2,\n  value: '\"value\": 1, \"type\": \"dis\", \"label\": \"Restrained (Entangle)\"'\n})\neffect.system.changes.push({\n  key: \"system.dynamicRollModifier.againstYou.attack\",\n  mode: 2,\n  value: '\"value\": 1, \"type\": \"adv\", \"label\": \"Restrained (Entangle)\"'\n})",
            "postItemRoll": ""
          },
          "rollLevelChange": false,
          "rollLevel": {
            "type": "adv",
            "value": 1
          },
          "addsRange": false,
          "bonusRange": {
            "melee": null,
            "normal": null,
            "max": null
          },
          "changeManaSpendLimit": 0,
          "changeStaminaSpendLimit": 0,
          "changeDuration": false,
          "duration": {
            "value": null,
            "type": "",
            "timeUnit": ""
          },
          "actionChange": false,
          "actionType": "",
          "areaDistance": "",
          "areaWidth": "",
          "overrideAreaType": ""
        },
        "key": "aTade7nOb9Uj6HSe",
        "sourceItemId": "cvsHJBsmJ6lTQpg4",
        "sourceItemName": "Entangle",
        "sourceItemImg": "icons/magic/nature/root-vine-entangled-humanoid.webp",
        "active": false,
        "repeatable": true,
        "defaultState": 0,
        "copyToSheetRoll": {},
        "altCostMax": 0,
        "altCost": 0,
        "drmCheck": false
      },
      "4GZEiQ03OyC73uhj": {
        "name": "Spikey Terrain",
        "number": 0,
        "preventModification": false,
        "description": "<p>Creatures take X Piercing damage when they enter an Entangled Space after the Spell has been cast. They also take this damage if they fail a Save to end the Immobilized Condition inflicted by this Spell.</p>",
        "hide": false,
        "resources": {
          "ap": "",
          "health": "",
          "mana": "1",
          "stamina": "",
          "grit": "",
          "restPoints": "",
          "custom": {}
        },
        "charges": {
          "subtract": null,
          "fromOriginal": false
        },
        "modifications": {
          "modifiesCoreFormula": false,
          "coreFormulaModification": "",
          "overrideTargetDefence": false,
          "targetDefenceType": "area",
          "hasAdditionalFormula": false,
          "additionalFormula": "",
          "specificFormulaKey": "",
          "overrideDamageType": false,
          "damageType": "",
          "addsNewFormula": false,
          "formula": {
            "formula": "",
            "type": "",
            "category": "damage",
            "fail": false,
            "failFormula": "",
            "dontModifyFailFormula": false,
            "each5": false,
            "each5Formula": "",
            "dontMerge": false,
            "overrideDefence": "",
            "perTarget": false
          },
          "addsNewRollRequest": false,
          "rollRequest": {
            "category": "save",
            "saveKey": "",
            "contestedKey": "",
            "dcCalculation": "spell",
            "dc": 0,
            "addMasteryToDC": true
          },
          "addsAgainstStatus": false,
          "againstStatus": {
            "id": "",
            "supressFromChatMessage": false,
            "untilYourNextTurnStart": false,
            "untilYourNextTurnEnd": false,
            "untilTargetNextTurnStart": false,
            "untilTargetNextTurnEnd": false,
            "untilFirstTimeTriggered": false,
            "forOneMinute": false,
            "repeatedSave": false,
            "repeatedSaveKey": "phy"
          },
          "addsEffect": {
            "name": "Spikey Terrain",
            "img": "icons/magic/nature/root-vine-thorned-coil-green.webp",
            "origin": null,
            "duration": {
              "rounds": 1,
              "startTime": 0,
              "combat": null,
              "seconds": null,
              "startRound": 1,
              "startTurn": 1,
              "value": 1,
              "units": "rounds",
              "expiry": "turnStart",
              "expired": false
            },
            "disabled": false,
            "flags": {
              "dc20rpg": {
                "enhKey": "4GZEiQ03OyC73uhj",
                "itemSavePath": "system.enhancements.4GZEiQ03OyC73uhj.modifications.addsEffect"
              }
            },
            "_id": "rpD8ybgB5FYWJvF2",
            "type": "base",
            "system": {
              "sustained": {
                "isSustained": false,
                "actorUuid": "",
                "itemId": ""
              },
              "statusId": "",
              "condition": false,
              "fromStatus": false,
              "duration": {
                "useCounter": false,
                "resetWhenEnabled": false,
                "onTimeEnd": "",
                "expiryAction": ""
              },
              "effectKey": "",
              "macro": "const spikeyTerrain = effect.flags.dc20rpg.spikeyTerrain || 0;\nif (!spikeyTerrain) return;\n\n// We dont want to call it too fast as some tokens might be inside that template at the time we place it.\nconst skipTime = 5000 // 5 sec\nconst templateCallTime = effect.flags.dc20rpg?.templateCallTime || 0;\nconst effectCreationTime = effect._stats.createdTime\nif (event.trigger === \"instant\" && effectCreationTime - templateCallTime < skipTime) return;\n\nlet dmg = {\n  value: spikeyTerrain,\n  source: \"Spikey Terrain\",\n  type: \"piercing\"\n}\nconst calculationTarget = {\n  system: {damageReduction: actor.system.damageReduction}\n}\ndmg = game.dc20rpg.tools.calculateForTarget(calculationTarget, {clear: {...dmg}, modified: {...dmg}}, {isDamage: true})\ngame.dc20rpg.tools.applyDamage(actor, dmg.modified, {fromEvent: true});",
              "addToChat": true,
              "applyToTemplate": true,
              "nonessential": false,
              "disableWhen": {
                "path": "",
                "mode": "",
                "value": ""
              },
              "enableStatusOnCreation": [],
              "disableStatusOnRemoval": [],
              "requireEnhancement": "",
              "chatMessageId": "",
              "changes": [
                {
                  "key": "system.events",
                  "value": "\"eventType\": \"macro\", \"trigger\": \"instant\", \"label\": \"Grasping\", \"actorId\": \"#SPEAKER_ID#\"",
                  "priority": null,
                  "useCustom": false,
                  "type": "add",
                  "phase": "initial"
                }
              ],
              "applyToSelf": false,
              "requireEquip": false,
              "refreshTarget": false
            },
            "description": "<p>Creature takes X Piercing damage when they enter an Entangled Space.</p>",
            "tint": "#ffffff",
            "transfer": false,
            "statuses": [],
            "sort": 0,
            "_stats": {
              "compendiumSource": null,
              "duplicateSource": null,
              "exportSource": null,
              "coreVersion": "14.364",
              "systemId": "dc20rpg",
              "systemVersion": "0.10.6.0",
              "createdTime": 1782422480493,
              "modifiedTime": 1782422480493,
              "lastModifiedBy": "dOcXwrUs2VunZl0y"
            },
            "start": {
              "combat": null,
              "round": 1,
              "time": 0,
              "turn": 1,
              "combatant": null,
              "initiative": null
            },
            "showIcon": 1,
            "folder": null
          },
          "macros": {
            "preItemRoll": "const entangle = item.getEffectByKey(\"entangle\");\nif (entangle) entangle.flags.dc20rpg.spikeyTerrain = enh.number;\n\nenh.modifications.addsEffect.flags.dc20rpg.spikeyTerrain = enh.number;",
            "postItemRoll": ""
          },
          "rollLevelChange": false,
          "rollLevel": {
            "type": "adv",
            "value": 1
          },
          "addsRange": false,
          "bonusRange": {
            "melee": null,
            "normal": null,
            "max": null
          },
          "changeManaSpendLimit": 0,
          "changeStaminaSpendLimit": 0,
          "changeDuration": false,
          "duration": {
            "value": null,
            "type": "",
            "timeUnit": ""
          },
          "actionChange": false,
          "actionType": "",
          "areaDistance": "",
          "areaWidth": "",
          "overrideAreaType": ""
        },
        "key": "4GZEiQ03OyC73uhj",
        "sourceItemId": "cvsHJBsmJ6lTQpg4",
        "sourceItemName": "Entangle",
        "sourceItemImg": "icons/magic/nature/root-vine-entangled-humanoid.webp",
        "active": false,
        "repeatable": true,
        "defaultState": 0,
        "copyToSheetRoll": {},
        "altCostMax": 0,
        "altCost": 0,
        "drmCheck": false
      }
    },
    "copyEnhancements": {
      "copy": false,
      "copyFor": "",
      "linkWithToggle": false,
      "hideFromRollMenu": false
    },
    "range": {
      "melee": 1,
      "normal": 5,
      "max": null,
      "unit": ""
    },
    "duration": {
      "value": 1,
      "type": "continuous",
      "timeUnit": "minutes"
    },
    "target": {
      "count": null,
      "type": "",
      "areas": {
        "default": {
          "area": "sphere",
          "distance": 3,
          "width": null,
          "unit": "",
          "difficult": "all"
        }
      }
    },
    "conditional": {
      "hasConditional": false,
      "name": "",
      "condition": "",
      "useFor": "",
      "linkWithToggle": false,
      "bonus": "0",
      "flags": {
        "ignorePdr": false,
        "ignoreEdr": false,
        "ignoreMdr": false,
        "ignoreResistance": {},
        "ignoreImmune": {}
      },
      "effect": null,
      "addsNewRollRequest": false,
      "rollRequest": {
        "category": "",
        "saveKey": "",
        "contestedKey": "",
        "dcCalculation": "",
        "dc": 0,
        "addMasteryToDC": true
      },
      "addsNewFormula": false,
      "formula": {
        "formula": "",
        "type": "",
        "category": "damage",
        "dontMerge": false,
        "overrideDefence": ""
      }
    },
    "conditionals": {},
    "hasAdvancement": false,
    "advancements": {
      "default": {
        "name": "Advancement",
        "customTitle": "",
        "tip": "",
        "level": 1,
        "applied": false,
        "additionalAdvancement": false,
        "repeatable": false,
        "repeatAt": [
          0,
          0,
          0,
          0,
          0,
          0,
          0,
          0,
          0,
          0,
          0,
          0,
          0,
          0,
          0,
          0,
          0,
          0,
          0,
          0,
          0
        ],
        "progressPath": false,
        "mustChoose": false,
        "doNotAddToKnownLimit": false,
        "pointAmount": 1,
        "talent": false,
        "allowToAddItems": false,
        "addItemsOptions": {
          "itemType": "",
          "preFilters": "",
          "helpText": "",
          "itemLimit": null
        },
        "macro": "",
        "items": {}
      }
    },
    "tip": "",
    "spellType": "spell",
    "spellSchool": "conjuration",
    "knownLimit": true,
    "usesWeapon": {
      "weaponAttack": false,
      "weaponId": ""
    },
    "effectsConfig": {
      "linkWithToggle": false,
      "toggleItem": true,
      "active": false,
      "addToChat": false,
      "addToTemplates": "all"
    },
    "spellSource": {
      "arcane": {
        "active": false,
        "label": "dc20rpg.spellSource.arcane"
      },
      "divine": {
        "active": false,
        "label": "dc20rpg.spellSource.divine"
      },
      "primal": {
        "active": true,
        "label": "dc20rpg.spellSource.primal"
      }
    },
    "components": {
      "verbal": {
        "active": true,
        "char": "V",
        "label": "dc20rpg.spellComponent.verbal"
      },
      "somatic": {
        "active": true,
        "char": "S",
        "label": "dc20rpg.spellComponent.somatic"
      },
      "material": {
        "active": false,
        "char": "M",
        "description": "",
        "cost": "",
        "consumed": false,
        "label": "dc20rpg.spellComponent.material"
      }
    },
    "spellTags": {
      "immobilized": "Immobilized",
      "plants": "Plants",
      "piercing": "Piercing",
      "restrained": "Restrained"
    },
    "areas": {
      "default": {
        "type": "sphere",
        "distance": 3,
        "width": null,
        "height": 1,
        "unit": "",
        "alwaysActive": false,
        "selfOnly": false,
        "linkWithToggle": false,
        "attachToToken": false,
        "blockByWalls": true,
        "effect": null,
        "difficultTerrain": "all",
        "applyEffectsFor": "all",
        "preventEffectRemoval": false,
        "preCreation": "",
        "postCreation": "",
        "hideHighlight": false
      }
    },
    "rollConfig": {
      "canCrit": false
    }
  },
  "effects": [
    {
      "name": "Entangle",
      "img": "icons/magic/nature/root-vine-entangled-humanoid.webp",
      "origin": "Item.HQyczaYtSdERgT9y",
      "duration": {
        "value": 5,
        "units": "rounds",
        "expiry": "turnStart",
        "expired": false
      },
      "disabled": false,
      "flags": {
        "dc20rpg": {}
      },
      "_id": "hsGGz4kIZVOXySyF",
      "type": "base",
      "system": {
        "sustained": {
          "isSustained": false,
          "actorUuid": "",
          "itemId": ""
        },
        "statusId": "",
        "condition": false,
        "fromStatus": false,
        "duration": {
          "useCounter": true,
          "resetWhenEnabled": false,
          "onTimeEnd": "delete",
          "expiryAction": "delete"
        },
        "effectKey": "entangle",
        "macro": "const spikeyTerrain = effect.flags.dc20rpg?.spikeyTerrain || 0;\n\nif (spikeyTerrain) {\n  let dmg = {\n    value: spikeyTerrain,\n    source: \"Spikey Terrain\",\n    type: \"piercing\"\n  }\n  const calculationTarget = {\n    system: {damageReduction: actor.system.damageReduction}\n  }\n  dmg = game.dc20rpg.tools.calculateForTarget(calculationTarget, {clear: {...dmg}, modified: {...dmg}}, {isDamage: true})\n  game.dc20rpg.tools.applyDamage(actor, dmg.modified, {fromEvent: true});\n}",
        "addToChat": true,
        "nonessential": false,
        "disableWhen": {
          "path": "",
          "mode": "",
          "value": ""
        },
        "enableStatusOnCreation": [],
        "disableStatusOnRemoval": [],
        "requireEnhancement": "",
        "chatMessageId": "",
        "applyToTemplate": true,
        "changes": [
          {
            "key": "system.events",
            "value": "\"eventType\": \"saveRequest\", \"trigger\": \"manual\", \"label\": \"Entangle\", \"preTrigger\": \"spendAP\", \"checkKey\": \"agi\", \"against\": <#@saveDC.value.spell#>, \"statuses\": [\"immobilized\"], \"onSuccess\": \"delete\", \"onFail\": \"runMacro\", \"actorId\": \"#SPEAKER_ID#\"",
            "priority": null,
            "type": "add"
          },
          {
            "key": "system.movement.ground.bonus",
            "value": -100,
            "priority": null,
            "type": "add"
          },
          {
            "key": "system.dynamicRollModifier.onYou.saves.agi",
            "value": "\"value\": 1, \"type\": \"dis\", \"label\": \"Immobilized\"",
            "priority": null,
            "type": "add"
          }
        ]
      },
      "description": "<p>You are under the effect of Entangle.</p>",
      "tint": "#ffffff",
      "transfer": false,
      "statuses": [
        "immobilized"
      ],
      "sort": 0,
      "_stats": {
        "compendiumSource": null,
        "duplicateSource": null,
        "exportSource": null,
        "coreVersion": "14.364",
        "systemId": "dc20rpg",
        "systemVersion": "0.10.6.0",
        "lastModifiedBy": "dOcXwrUs2VunZl0y",
        "createdTime": 1781983690273,
        "modifiedTime": 1782422228415
      },
      "showIcon": 2,
      "start": {
        "combat": null,
        "round": null,
        "time": 0,
        "turn": null,
        "combatant": null,
        "initiative": null
      },
      "folder": null,
      "_key": "!items.effects!cvsHJBsmJ6lTQpg4.hsGGz4kIZVOXySyF"
    }
  ],
  "folder": "oSwtE4idWkaIPpl6",
  "flags": {},
  "_stats": {
    "compendiumSource": null,
    "duplicateSource": null,
    "exportSource": null,
    "coreVersion": "14.363",
    "systemId": "dc20rpg",
    "systemVersion": "0.10.6.0",
    "createdTime": 1767802765144,
    "modifiedTime": 1782631486089,
    "lastModifiedBy": "dOcXwrUs2VunZl0y"
  },
  "ownership": {
    "default": 0,
    "dOcXwrUs2VunZl0y": 3
  },
  "_id": "cvsHJBsmJ6lTQpg4",
  "sort": 1300000,
  "_key": "!items!cvsHJBsmJ6lTQpg4"
}
